[
  {
    "id": "t"
  },
  {
    "class": "Compartment",
    "id": "C",
    "assignments": {
      "start_": "1"
    },
    "boundary": true
  },
  {
    "class": "Species",
    "id": "A",
    "assignments": {
      "start_": "30"
    },
    "compartment": "C"
  },
  {
    "class": "Species",
    "id": "B",
    "assignments": {
      "start_": "1"
    },
    "compartment": "C"
  },
  {
    "class": "Reaction",
    "id": "J0",
    "assignments": {
      "ode_": "1"
    },
    "actors": [
      {
        "target": "A",
        "stoichiometry": -1
      },
      {
        "target": "B",
        "stoichiometry": 2
      },
      {
        "target": "A",
        "stoichiometry": -2
      },
      {
        "target": "B",
        "stoichiometry": 1
      }
    ]
  },
  {
    "id": "volume",
    "units": "litre",
    "action": "defineUnit"
  },
  {
    "id": "area",
    "units": "metre^2",
    "action": "defineUnit"
  },
  {
    "id": "length",
    "units": "metre",
    "action": "defineUnit"
  },
  {
    "id": "substance",
    "units": "mole",
    "action": "defineUnit"
  },
  {
    "id": "time",
    "units": "second",
    "action": "defineUnit"
  }
]